[{"prefix":"Hon.","first_name":"Richard W.","last_name":"Allen","suffix":null,"name":"Hon. Richard W. Allen","filing_date":"11/08/2021","document_id":"20019653","year":2021,"district":"GA12","source_ptr_link":"https://disclosures-clerk.house.gov/public_disc/ptr-pdfs/2021/20019653.pdf","transactions":[{"owner":"self","transaction_date":"2020-05-14","ticker":"MMM","description":"3M Company","transaction_type":"sale_full","amount":"$1,001 - $15,000","cap_gains_over_200":false},{"owner":"self","transaction_date":"2020-05-14","ticker":"HD","description":"Home Depot Inc","transaction_type":"purchase","amount":"$1,001 - $15,000","cap_gains_over_200":false},{"owner":"self","transaction_date":"2020-04-15","ticker":"TFC","description":"Truist Financial Corporation","transaction_type":"sale_full","amount":"$15,001 - $50,000","cap_gains_over_200":false},{"owner":"self","transaction_date":"2020-02-20","ticker":"WMT","description":"Walmart Inc","transaction_type":"purchase","amount":"$1,001 - $15,000","cap_gains_over_200":false}],"transcribed_by":"Timothy Carambat"},{"prefix":"Hon.","first_name":"Richard W.","last_name":"Allen","suffix":null,"name":"Hon. Richard W. Allen","filing_date":"11/08/2021","document_id":"20019774","year":2021,"district":"GA12","source_ptr_link":"https://disclosures-clerk.house.gov/public_disc/ptr-pdfs/2021/20019774.pdf","transactions":[{"owner":null,"transaction_date":"2019-12-27","ticker":"TSS","description":"Total System Services Inc","transaction_type":"sale_full","amount":"$15,001 - $50,000","cap_gains_over_200":false},{"owner":null,"transaction_date":"2019-12-27","ticker":"UTX","description":"United Technologies Corporation","transaction_type":"sale_full","amount":"$1,001 - $15,000","cap_gains_over_200":false}],"transcribed_by":"Timothy Carambat"},{"prefix":"Hon.","first_name":"Richard W.","last_name":"Allen","suffix":null,"name":"Hon. Richard W. Allen","filing_date":"11/08/2021","document_id":"20019775","year":2021,"district":"GA12","source_ptr_link":"https://disclosures-clerk.house.gov/public_disc/ptr-pdfs/2021/20019775.pdf","transactions":[{"owner":"self","transaction_date":"2021-06-15","ticker":"DOV","description":"Dover Corporation","transaction_type":"purchase","amount":"$15,001 - $50,000","cap_gains_over_200":false}],"transcribed_by":"Timothy Carambat"},{"prefix":"Hon.","first_name":"Alan S.","last_name":"Lowenthal","suffix":null,"name":"Hon. Alan S. Lowenthal","filing_date":"11/08/2021","document_id":"20019776","year":2021,"district":"CA47","source_ptr_link":"https://disclosures-clerk.house.gov/public_disc/ptr-pdfs/2021/20019776.pdf","transactions":[{"owner":"joint","transaction_date":"2021-10-29","ticker":"BKNG","description":"Booking Holdings Inc","transaction_type":"sale_full","amount":"$1,001 - $15,000","cap_gains_over_200":false}],"transcribed_by":"Timothy Carambat"},{"prefix":"Hon.","first_name":"Alan S.","last_name":"Lowenthal","suffix":null,"name":"Hon. Alan S. Lowenthal","filing_date":"11/08/2021","document_id":"20019777","year":2021,"district":"CA47","source_ptr_link":"https://disclosures-clerk.house.gov/public_disc/ptr-pdfs/2021/20019777.pdf","transactions":[{"owner":"self","transaction_date":"2021-10-21","ticker":"BX","description":"Blackstone Inc","transaction_type":"sale_partial","amount":"$15,001 - $50,000","cap_gains_over_200":false},{"owner":"self","transaction_date":"2021-10-21","ticker":"ICE","description":"Intercontinental Exchange Inc","transaction_type":"sale_partial","amount":"$1,001 - $15,000","cap_gains_over_200":false},{"owner":"self","transaction_date":"2021-10-19","ticker":"TMO","description":"Thermo Fisher Scientific Inc","transaction_type":"purchase","amount":"$15,001 - $50,000","cap_gains_over_200":false}],"transcribed_by":"Timothy Carambat"}]