[{"prefix":"Hon.","first_name":"Patrick","last_name":"Fallon","suffix":null,"name":"Hon. Patrick Fallon","filing_date":"12/29/2021","document_id":"20020096","year":2021,"district":"TX04","source_ptr_link":"https://disclosures-clerk.house.gov/public_disc/ptr-pdfs/2021/20020096.pdf","transactions":[{"owner":null,"transaction_date":"2021-09-28","ticker":"ORCC","description":"Owl Rock Capital Corporation","transaction_type":"purchase","amount":"$50,001 - $100,000","cap_gains_over_200":false},{"owner":null,"transaction_date":"2021-11-30","ticker":"ORCC","description":"Owl Rock Capital Corporation","transaction_type":"purchase","amount":"$50,001 - $100,000","cap_gains_over_200":false},{"owner":null,"transaction_date":"2021-11-15","ticker":"PYPL","description":"PayPal Holdings Inc","transaction_type":"purchase","amount":"$100,001 - $250,000","cap_gains_over_200":false},{"owner":null,"transaction_date":"2021-11-15","ticker":"PYPL","description":"PayPal Holdings Inc","transaction_type":"purchase","amount":"$100,001 - $250,000","cap_gains_over_200":false}],"transcribed_by":"Timothy Carambat"},{"prefix":"Hon.","first_name":"Nancy","last_name":"Pelosi","suffix":null,"name":"Hon. Nancy Pelosi","filing_date":"12/29/2021","document_id":"20020106","year":2021,"district":"CA12","source_ptr_link":"https://disclosures-clerk.house.gov/public_disc/ptr-pdfs/2021/20020106.pdf","transactions":[{"owner":"self","transaction_date":"2021-12-17","ticker":"GOOG","description":"Alphabet Inc - Class C Capital - 10 CALL opts with strike of $2000 expiry 9/16/22","transaction_type":"purchase","amount":"$500,001 - $1,000,000","cap_gains_over_200":false},{"owner":"self","transaction_date":"2021-12-21","ticker":"MU","description":"Micron Technology Inc - 100 CALL opts with strike of $50 expiry 9/16/22","transaction_type":"purchase","amount":"$250,001 - $500,000","cap_gains_over_200":false},{"owner":"self","transaction_date":"2021-12-22","ticker":"--","description":"REOF XX LLC - addtional invesment in LLC which acquired 5 Courtyard Mariott hotels in Fairfax VA (1), Baltimore, MD (2), and San Antonio, TX(2)","transaction_type":"purchase","amount":"$50,001 - $100,000","cap_gains_over_200":false},{"owner":"self","transaction_date":"2021-12-20","ticker":"RBLX","description":"Roblox Corporation Class A - 100 CALL options with strike $100 expiry 1/20/23","transaction_type":"purchase","amount":"$250,001 - $500,000","cap_gains_over_200":false},{"owner":"self","transaction_date":"2021-12-20","ticker":"CRM","description":"Salesforce.com Inc - 100 CALL options with strike $210 expiry 1/20/23","transaction_type":"purchase","amount":"$500,001 - $1,000,000","cap_gains_over_200":false},{"owner":"self","transaction_date":"2021-12-20","ticker":"CRM","description":"Salesforce.com Inc - 30 CALL options with strike $210 expiry 1/20/23","transaction_type":"purchase","amount":"$100,001 - $250,000","cap_gains_over_200":false},{"owner":"self","transaction_date":"2021-12-17","ticker":"DIS","description":"Walt Disney Company - 50 CALL options with strike $210 expiry 1/20/23","transaction_type":"purchase","amount":"$100,001 - $250,000","cap_gains_over_200":false}],"transcribed_by":"Timothy Carambat"},{"prefix":"Hon.","first_name":"Debbie","last_name":"Wasserman Schultz","suffix":null,"name":"Hon. Debbie Wasserman Schultz","filing_date":"12/29/2021","document_id":"20020102","year":2021,"district":"FL23","source_ptr_link":"https://disclosures-clerk.house.gov/public_disc/ptr-pdfs/2021/20020102.pdf","transactions":[{"owner":"dependent","transaction_date":"2021-12-23","ticker":"QMCO","description":"Quantum Corporation","transaction_type":"purchase","amount":"$1,001 - $15,000","cap_gains_over_200":false},{"owner":"dependent","transaction_date":"2021-12-23","ticker":"QMCO","description":"Quantum Corporation","transaction_type":"purchase","amount":"$1,001 - $15,000","cap_gains_over_200":false},{"owner":"dependent","transaction_date":"2021-12-23","ticker":"QMCO","description":"Quantum Corporation","transaction_type":"purchase","amount":"$1,001 - $15,000","cap_gains_over_200":false}],"transcribed_by":"Timothy Carambat"}]